fancy/__init__.py
fancy/colors.py
fancy/dictprocess.py
fancy/dictselect.py
fancy/grid_search.py
fancy/image_utils.py
fancy/nn_utils.py
fancy/plotting.py
fancy/sampling.py
fancy/slicing.py
fancy/weighted_loss.py
fancy_utils-0.0.1.dist-info/LICENSE
fancy_utils-0.0.1.dist-info/METADATA
fancy_utils-0.0.1.dist-info/WHEEL
fancy_utils-0.0.1.dist-info/top_level.txt
fancy_utils-0.0.1.dist-info/RECORD
