Metadata-Version: 2.1
Name: fancy-utils
Version: 0.0.1
Summary: miscellaneous utils for plotting, colors, slicing, nested dictionaries and more
Home-page: https://github.com/imagirom/fancy
Author: Roman Remme
Author-email: roman.remme@gmx.de
Project-URL: Source, https://github.com/imagirom/fancy/
Keywords: fancy,utils,ipywidgets
Classifier: Development Status :: 3 - Alpha
Classifier: License :: OSI Approved :: MIT License
Classifier: Programming Language :: Python :: 3
Requires-Python: >=3, <4
License-File: LICENSE
Provides-Extra: plotting
Requires-Dist: numpy ; extra == 'plotting'
Requires-Dist: matplotlib ; extra == 'plotting'
Requires-Dist: ipywidgets ; extra == 'plotting'
